sampdfextractor/__init__.py
sampdfextractor/extractor.py
sampdfextractor/ocr_engine.py
sampdfextractor/utils.py
sampdfextractor-0.1.0.dist-info/licenses/LICENSE
sampdfextractor-0.1.0.dist-info/METADATA
sampdfextractor-0.1.0.dist-info/WHEEL
sampdfextractor-0.1.0.dist-info/top_level.txt
sampdfextractor-0.1.0.dist-info/RECORD
