Metadata-Version: 2.4
Name: sampdfextractor
Version: 0.1.0
Summary: Automatically detect and extract text from scanned and normal PDFs.
Home-page: https://github.com/sam670/sampdfextractor
Author: Samrendra Vishwakarma
Author-email: samrendradev@gmail.com
Requires-Python: >=3.8
License-File: LICENSE
Requires-Dist: PyMuPDF
Requires-Dist: easyocr
Requires-Dist: pandas
Requires-Dist: Pillow
Dynamic: author
Dynamic: author-email
Dynamic: description
Dynamic: description-content-type
Dynamic: home-page
Dynamic: license-file
Dynamic: requires-dist
Dynamic: requires-python
Dynamic: summary
